numdantic/__init__.py
numdantic/_numpy_typing.py
numdantic/_numpy_validation.py
numdantic/py.typed
numdantic-0.2.0.dist-info/METADATA
numdantic-0.2.0.dist-info/WHEEL
numdantic-0.2.0.dist-info/licenses/LICENSE
numdantic-0.2.0.dist-info/RECORD
