Metadata-Version: 2.4
Name: numdantic
Version: 0.2.0
Summary: Library for numpy typing support and numpy array validation with pydantic
Project-URL: Homepage, https://github.com/MilanStaffehl/numdantic
Project-URL: Issues, https://github.com/MilanStaffehl/numdantic/issues
Author: Milan Staffehl
License-File: LICENSE
Keywords: numpy,pydantic,type checking,type hints,types,typing,validation,verification
Classifier: Development Status :: 3 - Alpha
Classifier: Intended Audience :: Developers
Classifier: License :: OSI Approved :: MIT License
Classifier: Natural Language :: English
Classifier: Operating System :: OS Independent
Classifier: Programming Language :: Python
Classifier: Programming Language :: Python :: 3
Classifier: Programming Language :: Python :: 3.11
Classifier: Programming Language :: Python :: 3.12
Classifier: Programming Language :: Python :: 3.13
Classifier: Topic :: Software Development
Classifier: Typing :: Typed
Requires-Python: >=3.11
Requires-Dist: numpy<3.0.0
Requires-Dist: pydantic<3.0.0,>=2.5.2
Provides-Extra: dev
Requires-Dist: black; extra == 'dev'
Requires-Dist: commitizen; extra == 'dev'
Requires-Dist: flake8; extra == 'dev'
Requires-Dist: flake8-bugbear; extra == 'dev'
Requires-Dist: isort; extra == 'dev'
Requires-Dist: mypy; extra == 'dev'
Requires-Dist: pre-commit; extra == 'dev'
Requires-Dist: pytest; extra == 'dev'
Requires-Dist: pytest-mock>=3.11.1; extra == 'dev'
Requires-Dist: pytest-subtests>=0.12.0; extra == 'dev'
Requires-Dist: pytest>=7.0; extra == 'dev'
Requires-Dist: radon; extra == 'dev'
Provides-Extra: lint
Requires-Dist: black; extra == 'lint'
Requires-Dist: flake8; extra == 'lint'
Requires-Dist: flake8-bugbear; extra == 'lint'
Requires-Dist: isort; extra == 'lint'
Requires-Dist: mypy; extra == 'lint'
Requires-Dist: pytest-mock>=3.11.1; extra == 'lint'
Requires-Dist: pytest-subtests>=0.12.0; extra == 'lint'
Requires-Dist: pytest>=7.0; extra == 'lint'
Requires-Dist: radon; extra == 'lint'
Provides-Extra: test
Requires-Dist: pytest-mock>=3.11.1; extra == 'test'
Requires-Dist: pytest-subtests>=0.12.0; extra == 'test'
Requires-Dist: pytest>=7.0; extra == 'test'
